<?xml version="1.0" encoding="UTF-8"?>
<?xml-stylesheet href="/IGRP/images/IGRP/IGRP2.3/app/sistema_de_avaliacao_igrpweb/teste_realizado/Teste_realizado.xsl" type="text/xsl"?>
<rows>
    <link_img>/IGRP/images/IGRP/IGRP2.3</link_img>
    <title>Dummie XML prototype</title>
    <site>
        <welcome_note>Oba</welcome_note>
        <footer_note>2019 - Copyright NOSI v.190711</footer_note>
        <user_name>Hexagon</user_name>
        <button type="specific">
            <title>Sair</title>
            <app>DUA</app>
            <page />
            <link>#</link>
            <target>_self</target>
            <img>exit.png</img>
        </button>
    </site>
    <page>Teste_realizado</page>
    <app>sistema_de_avaliacao_igrpweb</app>
    <plsql>
        <action>index</action>
        <package_instance></package_instance>
        <package_db>nosi.webapps.sistema_de_avaliacao_igrpweb.pages</package_db>
        <package_html>Teste_realizado</package_html>
        <table_name></table_name>
        <with_replace>false</with_replace>
        <with_label>false</with_label>
        <with_biztalk>false</with_biztalk>
        <dynamic_menu>false</dynamic_menu>
        <copy_menu>false</copy_menu>
        <package_copy_db />
        <package_copy_html />
        <preserve_url>webapps?r=igrp/page/preserveUrl&amp;p_id=288</preserve_url>
    </plsql>
    <slide-menu file="../images/IGRP/IGRP2.3/xml/IGRP-slide-menu.xml?v=2" />
    <top_menu file="../images/IGRP/IGRP2.3/xml/IGRP-top_menu.xml?v=2" />
    <content>
        <title>Teste Realizado</title>
        <form_1 type="form" xml-type="form" gen-type="container" gen-group="">
            <fields>
                <conceitos_de_igrp_studio name="p_conceitos_de_igrp_studio" type="separator" maxlength="250" placeholder="" desclabel="false" right="false">
                    <label>CONCEITOS DE IGRP STUDIO</label>
                </conceitos_de_igrp_studio>
                <pergunta_1_sep name="p_pergunta_1_sep" type="separator" maxlength="250" placeholder="" desclabel="false" right="false">
                    <label>Pergunta 1</label>
                </pergunta_1_sep>
                <pergunta1 name="p_pergunta1" type="plaintext" clear="false" disable_output_escaping="false" html_class="" maxlength="250" right="false">
                    <label>Pergunta1</label>
                    <value>Elit rem adipiscing amet doloremque perspiciatis stract aliqua elit laudantium rem totam iste natus lorem omnis aliqua sit laudantium totam doloremque natus magna labore sit</value>
                </pergunta1>
                <resposta1 name="p_resposta1" type="radiolist" domain="" maxlength="250" required="true" change="false" readonly="false" disabled="false" child_size="12" right="false" java-type="">
                    <label/>
                    <list>
                        <option>
                            <text>Option 1</text>
                            <value>1</value>
                        </option>
                        <option>
                            <text>Option 2</text>
                            <value>2</value>
                        </option>
                        <option>
                            <text>Option 3</text>
                            <value>3</value>
                        </option>
                        <option>
                            <text>Option 4</text>
                            <value>4</value>
                        </option>
                    </list>
                    <validations>
                        <validation>
                            <annotation>@NotNull</annotation>
                        </validation>
                    </validations>
                </resposta1>
                <pergunta_2_sep name="p_pergunta_2_sep" type="separator" maxlength="250" placeholder="" desclabel="false" right="false">
                    <label>Pergunta 2</label>
                </pergunta_2_sep>
                <pergunta2 name="p_pergunta2" type="plaintext" clear="false" disable_output_escaping="false" html_class="" maxlength="250" right="false">
                    <label>Pergunta2</label>
                    <value>Aliqua accusantium sed doloremque adipiscing laudantium magna dolor aliqua amet iste ipsum perspiciatis labore elit magna iste dolor anim adipiscing sed stract unde totam mollit</value>
                </pergunta2>
                <resposta2 name="p_resposta2" type="radiolist" domain="" maxlength="250" required="true" change="false" readonly="false" disabled="false" child_size="12" right="false" java-type="">
                    <label/>
                    <list>
                        <option>
                            <text>Option 1</text>
                            <value>1</value>
                        </option>
                        <option>
                            <text>Option 2</text>
                            <value>2</value>
                        </option>
                        <option>
                            <text>Option 3</text>
                            <value>3</value>
                        </option>
                        <option>
                            <text>Option 4</text>
                            <value>4</value>
                        </option>
                    </list>
                </resposta2>
                <pergunta_3_sep name="p_pergunta_3_sep" type="separator" maxlength="250" placeholder="" desclabel="false" right="false">
                    <label>Pergunta 3</label>
                </pergunta_3_sep>
                <pergunta_3 name="p_pergunta_3" type="plaintext" clear="false" disable_output_escaping="false" html_class="" maxlength="250" right="false">
                    <label>Pergunta 3</label>
                    <value>Consectetur perspiciatis iste sed totam aperiam magna lorem magna aliqua iste lorem stract ipsum natus aliqua stract unde aperiam lorem magna unde mollit totam perspiciatis</value>
                </pergunta_3>
                <resposta3 name="p_resposta3" type="radiolist" domain="" maxlength="250" required="true" change="false" readonly="false" disabled="false" child_size="12" right="false" java-type="">
                    <label/>
                    <list>
                        <option>
                            <text>Option 1</text>
                            <value>1</value>
                        </option>
                        <option>
                            <text>Option 2</text>
                            <value>2</value>
                        </option>
                        <option>
                            <text>Option 3</text>
                            <value>3</value>
                        </option>
                        <option>
                            <text>Option 4</text>
                            <value>4</value>
                        </option>
                    </list>
                </resposta3>
                <pergunta_4_sep name="p_pergunta_4_sep" type="separator" maxlength="250" placeholder="" desclabel="false" right="false">
                    <label>Pergunta 4</label>
                </pergunta_4_sep>
                <pergunta_4 name="p_pergunta_4" type="plaintext" clear="false" disable_output_escaping="false" html_class="" maxlength="250" right="false">
                    <label>Pergunta 4</label>
                    <value>Stract magna accusantium iste stract rem ut omnis sed aperiam accusantium sed laudantium deserunt omnis amet magna elit perspiciatis doloremque elit laudantium sit omnis aperiam</value>
                </pergunta_4>
                <resposta4 name="p_resposta4" type="radiolist" domain="" maxlength="250" required="true" change="false" readonly="false" disabled="false" child_size="12" right="false" java-type="">
                    <label/>
                    <list>
                        <option>
                            <text>Option 1</text>
                            <value>1</value>
                        </option>
                        <option>
                            <text>Option 2</text>
                            <value>2</value>
                        </option>
                        <option>
                            <text>Option 3</text>
                            <value>3</value>
                        </option>
                        <option>
                            <text>Option 4</text>
                            <value>4</value>
                        </option>
                    </list>
                    <validations>
                        <validation>
                            <annotation>@NotNull</annotation>
                        </validation>
                    </validations>
                </resposta4>
                <pergunta_5_sep name="p_pergunta_5_sep" type="separator" maxlength="250" placeholder="" desclabel="false" right="false">
                    <label>Pergunta 5</label>
                </pergunta_5_sep>
                <pergunta_5 name="p_pergunta_5" type="plaintext" clear="false" disable_output_escaping="false" html_class="" maxlength="250" right="false">
                    <label>Pergunta 5</label>
                    <value>Natus iste aliqua perspiciatis sit laudantium accusantium aliqua iste lorem anim voluptatem ipsum perspiciatis dolor doloremque dolor sit consectetur dolor mollit natus aperiam amet sed</value>
                </pergunta_5>
                <resposta5 name="p_resposta5" type="radiolist" domain="" maxlength="250" required="true" change="false" readonly="false" disabled="false" child_size="12" right="false" java-type="">
                    <label/>
                    <list>
                        <option>
                            <text>Option 1</text>
                            <value>1</value>
                        </option>
                        <option>
                            <text>Option 2</text>
                            <value>2</value>
                        </option>
                        <option>
                            <text>Option 3</text>
                            <value>3</value>
                        </option>
                        <option>
                            <text>Option 4</text>
                            <value>4</value>
                        </option>
                    </list>
                    <validations>
                        <validation>
                            <annotation>@NotNull</annotation>
                        </validation>
                    </validations>
                </resposta5>
                <conceitos_bpmn__e_report_designer name="p_conceitos_bpmn__e_report_designer" type="separator" maxlength="250" placeholder="" desclabel="false" right="false">
                    <label>CONCEITOS BPMN  E REPORT DESIGNER</label>
                </conceitos_bpmn__e_report_designer>
                <pergunta_6_sep name="p_pergunta_6_sep" type="separator" maxlength="250" placeholder="" desclabel="false" right="false">
                    <label>Pergunta 6</label>
                </pergunta_6_sep>
                <pergunta_6 name="p_pergunta_6" type="plaintext" clear="false" disable_output_escaping="false" html_class="" maxlength="250" right="false">
                    <label>Pergunta 6</label>
                    <value>Lorem aliqua labore sed perspiciatis totam ipsum sed perspiciatis lorem officia accusantium doloremque voluptatem totam deserunt anim magna aliqua iste adipiscing stract unde omnis elit</value>
                </pergunta_6>
                <resposta6 name="p_resposta6" type="radiolist" domain="" maxlength="250" required="true" change="false" readonly="false" disabled="false" child_size="12" right="false" java-type="">
                    <label/>
                    <list>
                        <option>
                            <text>Option 1</text>
                            <value>1</value>
                        </option>
                        <option>
                            <text>Option 2</text>
                            <value>2</value>
                        </option>
                        <option>
                            <text>Option 3</text>
                            <value>3</value>
                        </option>
                        <option>
                            <text>Option 4</text>
                            <value>4</value>
                        </option>
                    </list>
                    <validations>
                        <validation>
                            <annotation>@NotNull</annotation>
                        </validation>
                    </validations>
                </resposta6>
                <pergunta_7_sep name="p_pergunta_7_sep" type="separator" maxlength="250" placeholder="" desclabel="false" right="false">
                    <label>Pergunta 7</label>
                </pergunta_7_sep>
                <pergunta_7 name="p_pergunta_7" type="plaintext" clear="false" disable_output_escaping="false" html_class="" maxlength="250" right="false">
                    <label>Pergunta 7</label>
                    <value>Amet rem deserunt elit officia consectetur natus mollit consectetur amet rem adipiscing doloremque magna sit consectetur natus aperiam aliqua mollit officia natus totam aperiam adipiscing</value>
                </pergunta_7>
                <resposta7 name="p_resposta7" type="radiolist" domain="" maxlength="250" required="true" change="false" readonly="false" disabled="false" child_size="12" right="false" java-type="">
                    <label/>
                    <list>
                        <option>
                            <text>Option 1</text>
                            <value>1</value>
                        </option>
                        <option>
                            <text>Option 2</text>
                            <value>2</value>
                        </option>
                        <option>
                            <text>Option 3</text>
                            <value>3</value>
                        </option>
                        <option>
                            <text>Option 4</text>
                            <value>4</value>
                        </option>
                    </list>
                    <validations>
                        <validation>
                            <annotation>@NotNull</annotation>
                        </validation>
                    </validations>
                </resposta7>
                <pergunta_8_sep name="p_pergunta_8_sep" type="separator" maxlength="250" placeholder="" desclabel="false" right="false">
                    <label>Pergunta 8</label>
                </pergunta_8_sep>
                <pergunta8 name="p_pergunta8" type="plaintext" clear="false" disable_output_escaping="false" html_class="" maxlength="250" right="false">
                    <label>Pergunta8</label>
                    <value>Amet iste magna lorem sit doloremque deserunt ut elit labore dolor labore doloremque stract aperiam natus unde adipiscing ut mollit laudantium deserunt voluptatem ipsum magna</value>
                </pergunta8>
                <resposta8 name="p_resposta8" type="radiolist" domain="" maxlength="250" required="true" change="false" readonly="false" disabled="false" child_size="12" right="false" java-type="">
                    <label/>
                    <list>
                        <option>
                            <text>Option 1</text>
                            <value>1</value>
                        </option>
                        <option>
                            <text>Option 2</text>
                            <value>2</value>
                        </option>
                        <option>
                            <text>Option 3</text>
                            <value>3</value>
                        </option>
                        <option>
                            <text>Option 4</text>
                            <value>4</value>
                        </option>
                    </list>
                    <validations>
                        <validation>
                            <annotation>@NotNull</annotation>
                        </validation>
                    </validations>
                </resposta8>
                <pergunta_9_sep name="p_pergunta_9_sep" type="separator" maxlength="250" placeholder="" desclabel="false" right="false">
                    <label>Pergunta 9</label>
                </pergunta_9_sep>
                <pergunta9 name="p_pergunta9" type="plaintext" clear="false" disable_output_escaping="false" html_class="" maxlength="250" right="false">
                    <label>Pergunta9</label>
                    <value>Doloremque voluptatem doloremque anim omnis consectetur labore anim aperiam sed laudantium voluptatem elit doloremque ut adipiscing consectetur amet perspiciatis doloremque totam officia natus lorem rem</value>
                </pergunta9>
                <resposta9 name="p_resposta9" type="radiolist" domain="" maxlength="250" required="true" change="false" readonly="false" disabled="false" child_size="12" right="false" java-type="">
                    <label/>
                    <list>
                        <option>
                            <text>Option 1</text>
                            <value>1</value>
                        </option>
                        <option>
                            <text>Option 2</text>
                            <value>2</value>
                        </option>
                        <option>
                            <text>Option 3</text>
                            <value>3</value>
                        </option>
                        <option>
                            <text>Option 4</text>
                            <value>4</value>
                        </option>
                    </list>
                    <validations>
                        <validation>
                            <annotation>@NotNull</annotation>
                        </validation>
                    </validations>
                </resposta9>
                <pergunta_10_sep name="p_pergunta_10_sep" type="separator" maxlength="250" placeholder="" desclabel="false" right="false">
                    <label>Pergunta 10</label>
                </pergunta_10_sep>
                <pergunta10 name="p_pergunta10" type="plaintext" clear="false" disable_output_escaping="false" html_class="" maxlength="250" right="false">
                    <label>Pergunta10</label>
                    <value>Amet consectetur rem laudantium magna totam labore adipiscing laudantium voluptatem doloremque perspiciatis anim stract amet stract sed iste accusantium iste adipiscing sit lorem sed adipiscing</value>
                </pergunta10>
                <resposta10 name="p_resposta10" type="radiolist" domain="" maxlength="250" required="true" change="false" readonly="false" disabled="false" child_size="12" right="false" java-type="">
                    <label/>
                    <list>
                        <option>
                            <text>Option 1</text>
                            <value>1</value>
                        </option>
                        <option>
                            <text>Option 2</text>
                            <value>2</value>
                        </option>
                        <option>
                            <text>Option 3</text>
                            <value>3</value>
                        </option>
                        <option>
                            <text>Option 4</text>
                            <value>4</value>
                        </option>
                    </list>
                    <validations>
                        <validation>
                            <annotation>@NotNull</annotation>
                        </validation>
                    </validations>
                </resposta10>
                <conceitos_page_designer name="p_conceitos_page_designer" type="separator" maxlength="250" placeholder="" desclabel="false" right="false">
                    <label>CONCEITOS PAGE DESIGNER</label>
                </conceitos_page_designer>
                <pergunta_11_sep name="p_pergunta_11_sep" type="separator" maxlength="250" placeholder="" desclabel="false" right="false">
                    <label>Pergunta 11</label>
                </pergunta_11_sep>
                <pergunta11 name="p_pergunta11" type="plaintext" clear="false" disable_output_escaping="false" html_class="" maxlength="250" right="false">
                    <label>Pergunta11</label>
                    <value>Doloremque omnis ut unde rem rem elit ut unde ipsum labore dolor accusantium doloremque totam omnis sed dolor ipsum aperiam aliqua perspiciatis ipsum laudantium mollit</value>
                </pergunta11>
                <resposta11 name="p_resposta11" type="radiolist" domain="" maxlength="250" required="true" change="false" readonly="false" disabled="false" child_size="12" right="false" java-type="">
                    <label/>
                    <list>
                        <option>
                            <text>Option 1</text>
                            <value>1</value>
                        </option>
                        <option>
                            <text>Option 2</text>
                            <value>2</value>
                        </option>
                        <option>
                            <text>Option 3</text>
                            <value>3</value>
                        </option>
                        <option>
                            <text>Option 4</text>
                            <value>4</value>
                        </option>
                    </list>
                    <validations>
                        <validation>
                            <annotation>@NotNull</annotation>
                        </validation>
                    </validations>
                </resposta11>
                <pergunta_12_sep name="p_pergunta_12_sep" type="separator" maxlength="250" placeholder="" desclabel="false" right="false">
                    <label>Pergunta 12</label>
                </pergunta_12_sep>
                <pergunta12 name="p_pergunta12" type="plaintext" clear="false" disable_output_escaping="false" html_class="" maxlength="250" right="false">
                    <label>Pergunta12</label>
                    <value>Unde officia sed dolor rem sit ipsum accusantium sed rem magna iste rem aperiam deserunt adipiscing dolor adipiscing sit aliqua voluptatem adipiscing mollit voluptatem stract</value>
                </pergunta12>
                <resposta12 name="p_resposta12" type="radiolist" domain="" maxlength="250" required="true" change="false" readonly="false" disabled="false" child_size="12" right="false" java-type="">
                    <label/>
                    <list>
                        <option>
                            <text>Option 1</text>
                            <value>1</value>
                        </option>
                        <option>
                            <text>Option 2</text>
                            <value>2</value>
                        </option>
                        <option>
                            <text>Option 3</text>
                            <value>3</value>
                        </option>
                        <option>
                            <text>Option 4</text>
                            <value>4</value>
                        </option>
                    </list>
                    <validations>
                        <validation>
                            <annotation>@NotNull</annotation>
                        </validation>
                    </validations>
                </resposta12>
                <pergunta_13_sep name="p_pergunta_13_sep" type="separator" maxlength="250" placeholder="" desclabel="false" right="false">
                    <label>Pergunta 13</label>
                </pergunta_13_sep>
                <pergunta13 name="p_pergunta13" type="plaintext" clear="false" disable_output_escaping="false" html_class="" maxlength="250" right="false">
                    <label>Pergunta13</label>
                    <value>Magna ut aperiam elit totam perspiciatis ut doloremque unde omnis mollit sit deserunt labore sit adipiscing sit accusantium totam rem adipiscing mollit stract officia perspiciatis</value>
                </pergunta13>
                <resposta13 name="p_resposta13" type="radiolist" domain="" maxlength="250" required="true" change="false" readonly="false" disabled="false" child_size="12" right="false" java-type="">
                    <label/>
                    <list>
                        <option>
                            <text>Option 1</text>
                            <value>1</value>
                        </option>
                        <option>
                            <text>Option 2</text>
                            <value>2</value>
                        </option>
                        <option>
                            <text>Option 3</text>
                            <value>3</value>
                        </option>
                        <option>
                            <text>Option 4</text>
                            <value>4</value>
                        </option>
                    </list>
                    <validations>
                        <validation>
                            <annotation>@NotNull</annotation>
                        </validation>
                    </validations>
                </resposta13>
                <pergunta_14_sep name="p_pergunta_14_sep" type="separator" maxlength="250" placeholder="" desclabel="false" right="false">
                    <label>Pergunta 14</label>
                </pergunta_14_sep>
                <pergunta14 name="p_pergunta14" type="plaintext" clear="false" disable_output_escaping="false" html_class="" maxlength="250" right="false">
                    <label>Pergunta14</label>
                    <value>Omnis rem rem elit adipiscing elit labore aliqua elit anim stract aperiam voluptatem officia ut unde adipiscing doloremque accusantium consectetur dolor aliqua dolor magna sed</value>
                </pergunta14>
                <resposta14 name="p_resposta14" type="radiolist" domain="" maxlength="250" required="true" change="false" readonly="false" disabled="false" child_size="12" right="false" java-type="">
                    <label/>
                    <list>
                        <option>
                            <text>Option 1</text>
                            <value>1</value>
                        </option>
                        <option>
                            <text>Option 2</text>
                            <value>2</value>
                        </option>
                        <option>
                            <text>Option 3</text>
                            <value>3</value>
                        </option>
                        <option>
                            <text>Option 4</text>
                            <value>4</value>
                        </option>
                    </list>
                    <validations>
                        <validation>
                            <annotation>@NotNull</annotation>
                        </validation>
                    </validations>
                </resposta14>
                <pergunta_15_sep name="p_pergunta_15_sep" type="separator" maxlength="250" placeholder="" desclabel="false" right="false">
                    <label>Pergunta 15</label>
                </pergunta_15_sep>
                <pergunta15 name="p_pergunta15" type="plaintext" clear="false" disable_output_escaping="false" html_class="" maxlength="250" right="false">
                    <label>Pergunta15</label>
                    <value>Laudantium aliqua adipiscing ipsum magna elit perspiciatis ut rem doloremque accusantium sit omnis officia omnis consectetur sed natus unde consectetur officia rem consectetur aliqua lorem</value>
                </pergunta15>
                <resposta15 name="p_resposta15" type="radiolist" domain="" maxlength="250" required="true" change="false" readonly="false" disabled="false" child_size="12" right="false" java-type="">
                    <label/>
                    <list>
                        <option>
                            <text>Option 1</text>
                            <value>1</value>
                        </option>
                        <option>
                            <text>Option 2</text>
                            <value>2</value>
                        </option>
                        <option>
                            <text>Option 3</text>
                            <value>3</value>
                        </option>
                        <option>
                            <text>Option 4</text>
                            <value>4</value>
                        </option>
                    </list>
                    <validations>
                        <validation>
                            <annotation>@NotNull</annotation>
                        </validation>
                    </validations>
                </resposta15>
                <conceitos_gerador_de_codigo_e_blockly name="p_conceitos_gerador_de_codigo_e_blockly" type="separator" maxlength="250" placeholder="" desclabel="false" right="false">
                    <label>CONCEITOS GERADOR DE CÓDIGO E BLOCKLY</label>
                </conceitos_gerador_de_codigo_e_blockly>
                <pergunta_16_sep name="p_pergunta_16_sep" type="separator" maxlength="250" placeholder="" desclabel="false" right="false">
                    <label>Pergunta 16</label>
                </pergunta_16_sep>
                <pergunta16 name="p_pergunta16" type="plaintext" clear="false" disable_output_escaping="false" html_class="" maxlength="250" right="false">
                    <label>Pergunta16</label>
                    <value>Stract anim stract natus aliqua dolor laudantium sed perspiciatis anim stract unde laudantium deserunt sed stract sit laudantium officia doloremque ipsum anim rem stract natus</value>
                </pergunta16>
                <resposta16 name="p_resposta16" type="radiolist" domain="" maxlength="250" required="true" change="false" readonly="false" disabled="false" child_size="12" right="false" java-type="">
                    <label/>
                    <list>
                        <option>
                            <text>Option 1</text>
                            <value>1</value>
                        </option>
                        <option>
                            <text>Option 2</text>
                            <value>2</value>
                        </option>
                        <option>
                            <text>Option 3</text>
                            <value>3</value>
                        </option>
                        <option>
                            <text>Option 4</text>
                            <value>4</value>
                        </option>
                    </list>
                    <validations>
                        <validation>
                            <annotation>@NotNull</annotation>
                        </validation>
                    </validations>
                </resposta16>
                <pergunta_17_sep name="p_pergunta_17_sep" type="separator" maxlength="250" placeholder="" desclabel="false" right="false">
                    <label>Pergunta 17</label>
                </pergunta_17_sep>
                <pergunta17 name="p_pergunta17" type="plaintext" clear="false" disable_output_escaping="false" html_class="" maxlength="250" right="false">
                    <label>Pergunta17</label>
                    <value>Stract accusantium sit natus deserunt omnis rem accusantium rem sit anim elit omnis natus aliqua lorem dolor rem lorem deserunt unde ut lorem doloremque sit</value>
                </pergunta17>
                <resposta17 name="p_resposta17" type="radiolist" domain="" maxlength="250" required="true" change="false" readonly="false" disabled="false" child_size="12" right="false" java-type="">
                    <label/>
                    <list>
                        <option>
                            <text>Option 1</text>
                            <value>1</value>
                        </option>
                        <option>
                            <text>Option 2</text>
                            <value>2</value>
                        </option>
                        <option>
                            <text>Option 3</text>
                            <value>3</value>
                        </option>
                        <option>
                            <text>Option 4</text>
                            <value>4</value>
                        </option>
                    </list>
                    <validations>
                        <validation>
                            <annotation>@NotNull</annotation>
                        </validation>
                    </validations>
                </resposta17>
                <pergunta_18_sep name="p_pergunta_18_sep" type="separator" maxlength="250" placeholder="" desclabel="false" right="false">
                    <label>Pergunta 18</label>
                </pergunta_18_sep>
                <pergunta18 name="p_pergunta18" type="plaintext" clear="false" disable_output_escaping="false" html_class="" maxlength="250" right="false">
                    <label>Pergunta18</label>
                    <value>Lorem laudantium natus stract ut voluptatem sit deserunt iste ipsum amet deserunt adipiscing officia laudantium totam sit anim aliqua dolor voluptatem natus ut doloremque ipsum</value>
                </pergunta18>
                <resposta18 name="p_resposta18" type="radiolist" domain="" maxlength="250" required="true" change="false" readonly="false" disabled="false" child_size="12" right="false" java-type="">
                    <label/>
                    <list>
                        <option>
                            <text>Option 1</text>
                            <value>1</value>
                        </option>
                        <option>
                            <text>Option 2</text>
                            <value>2</value>
                        </option>
                        <option>
                            <text>Option 3</text>
                            <value>3</value>
                        </option>
                        <option>
                            <text>Option 4</text>
                            <value>4</value>
                        </option>
                    </list>
                    <validations>
                        <validation>
                            <annotation>@NotNull</annotation>
                        </validation>
                    </validations>
                </resposta18>
                <pergunta_19_sep name="p_pergunta_19_sep" type="separator" maxlength="250" placeholder="" desclabel="false" right="false">
                    <label>Pergunta 19</label>
                </pergunta_19_sep>
                <pergunta19 name="p_pergunta19" type="plaintext" clear="false" disable_output_escaping="false" html_class="" maxlength="250" right="false">
                    <label>Pergunta19</label>
                    <value>Aliqua labore omnis totam sed lorem unde elit omnis officia voluptatem consectetur rem aperiam aliqua voluptatem ut anim unde deserunt sed magna laudantium sit aliqua</value>
                </pergunta19>
                <resposta19 name="p_resposta19" type="radiolist" domain="" maxlength="250" required="true" change="false" readonly="false" disabled="false" child_size="12" right="false" java-type="">
                    <label/>
                    <list>
                        <option>
                            <text>Option 1</text>
                            <value>1</value>
                        </option>
                        <option>
                            <text>Option 2</text>
                            <value>2</value>
                        </option>
                        <option>
                            <text>Option 3</text>
                            <value>3</value>
                        </option>
                        <option>
                            <text>Option 4</text>
                            <value>4</value>
                        </option>
                    </list>
                    <validations>
                        <validation>
                            <annotation>@NotNull</annotation>
                        </validation>
                    </validations>
                </resposta19>
                <pergunta_20sep name="p_pergunta_20sep" type="separator" maxlength="250" placeholder="" desclabel="false" right="false">
                    <label>Pergunta 20</label>
                </pergunta_20sep>
                <pergunta20 name="p_pergunta20" type="plaintext" clear="false" disable_output_escaping="false" html_class="" maxlength="250" right="false">
                    <label>Pergunta20</label>
                    <value>Sit doloremque sit aperiam mollit adipiscing ipsum omnis anim magna natus aperiam doloremque totam sit iste elit doloremque iste officia lorem sed elit laudantium amet</value>
                </pergunta20>
                <resposta20 name="p_resposta20" type="radiolist" domain="" maxlength="250" required="true" change="false" readonly="false" disabled="false" child_size="12" right="false" java-type="">
                    <label/>
                    <list>
                        <option>
                            <text>Option 1</text>
                            <value>1</value>
                        </option>
                        <option>
                            <text>Option 2</text>
                            <value>2</value>
                        </option>
                        <option>
                            <text>Option 3</text>
                            <value>3</value>
                        </option>
                        <option>
                            <text>Option 4</text>
                            <value>4</value>
                        </option>
                    </list>
                    <validations>
                        <validation>
                            <annotation>@NotNull</annotation>
                        </validation>
                    </validations>
                </resposta20>
                <conceitos_de_eclipse_e_git name="p_conceitos_de_eclipse_e_git" type="separator" maxlength="250" placeholder="" desclabel="false" right="false">
                    <label>CONCEITOS DE ECLIPSE E GIT</label>
                </conceitos_de_eclipse_e_git>
                <pergunta_21_sep name="p_pergunta_21_sep" type="separator" maxlength="250" placeholder="" desclabel="false" right="false">
                    <label>Pergunta 21</label>
                </pergunta_21_sep>
                <pergunta21 name="p_pergunta21" type="plaintext" clear="false" disable_output_escaping="false" html_class="" maxlength="250" right="false">
                    <label>Pergunta21</label>
                    <value>Natus aperiam magna mollit laudantium elit stract amet perspiciatis stract doloremque accusantium dolor aperiam dolor magna elit doloremque sed laudantium sit omnis elit anim magna</value>
                </pergunta21>
                <resposta21 name="p_resposta21" type="radiolist" domain="" maxlength="250" required="true" change="false" readonly="false" disabled="false" child_size="12" right="false" java-type="">
                    <label/>
                    <list>
                        <option>
                            <text>Option 1</text>
                            <value>1</value>
                        </option>
                        <option>
                            <text>Option 2</text>
                            <value>2</value>
                        </option>
                        <option>
                            <text>Option 3</text>
                            <value>3</value>
                        </option>
                        <option>
                            <text>Option 4</text>
                            <value>4</value>
                        </option>
                    </list>
                    <validations>
                        <validation>
                            <annotation>@NotNull</annotation>
                        </validation>
                    </validations>
                </resposta21>
                <pergunta_22_sep name="p_pergunta_22_sep" type="separator" maxlength="250" placeholder="" desclabel="false" right="false">
                    <label>Pergunta 22</label>
                </pergunta_22_sep>
                <pergunta22 name="p_pergunta22" type="plaintext" clear="false" disable_output_escaping="false" html_class="" maxlength="250" right="false">
                    <label>Pergunta22</label>
                    <value>Ipsum amet aliqua officia lorem anim ut dolor labore ipsum magna anim omnis doloremque laudantium mollit elit lorem deserunt magna mollit unde sit amet aliqua</value>
                </pergunta22>
                <resposta22 name="p_resposta22" type="radiolist" domain="" maxlength="250" required="true" change="false" readonly="false" disabled="false" child_size="12" right="false" java-type="">
                    <label/>
                    <list>
                        <option>
                            <text>Option 1</text>
                            <value>1</value>
                        </option>
                        <option>
                            <text>Option 2</text>
                            <value>2</value>
                        </option>
                        <option>
                            <text>Option 3</text>
                            <value>3</value>
                        </option>
                        <option>
                            <text>Option 4</text>
                            <value>4</value>
                        </option>
                    </list>
                    <validations>
                        <validation>
                            <annotation>@NotNull</annotation>
                        </validation>
                    </validations>
                </resposta22>
                <pergunta_23_sep name="p_pergunta_23_sep" type="separator" maxlength="250" placeholder="" desclabel="false" right="false">
                    <label>Pergunta 23</label>
                </pergunta_23_sep>
                <pergunta23 name="p_pergunta23" type="plaintext" clear="false" disable_output_escaping="false" html_class="" maxlength="250" right="false">
                    <label>Pergunta23</label>
                    <value>Totam adipiscing officia totam iste aperiam ut magna amet lorem natus amet rem laudantium perspiciatis doloremque deserunt sed lorem ut elit magna lorem ipsum consectetur</value>
                </pergunta23>
                <resposta23 name="p_resposta23" type="radiolist" domain="" maxlength="250" required="true" change="false" readonly="false" disabled="false" child_size="12" right="false" java-type="">
                    <label/>
                    <list>
                        <option>
                            <text>Option 1</text>
                            <value>1</value>
                        </option>
                        <option>
                            <text>Option 2</text>
                            <value>2</value>
                        </option>
                        <option>
                            <text>Option 3</text>
                            <value>3</value>
                        </option>
                        <option>
                            <text>Option 4</text>
                            <value>4</value>
                        </option>
                    </list>
                    <validations>
                        <validation>
                            <annotation>@NotNull</annotation>
                        </validation>
                    </validations>
                </resposta23>
                <pergunta_24_sep name="p_pergunta_24_sep" type="separator" maxlength="250" placeholder="" desclabel="false" right="false">
                    <label>Pergunta 24</label>
                </pergunta_24_sep>
                <pergunta24 name="p_pergunta24" type="plaintext" clear="false" disable_output_escaping="false" html_class="" maxlength="250" right="false">
                    <label>Pergunta24</label>
                    <value>Deserunt elit sed aliqua dolor rem aliqua consectetur sit sit rem aliqua adipiscing consectetur laudantium elit voluptatem mollit anim officia totam dolor sed iste consectetur</value>
                </pergunta24>
                <resposta24 name="p_resposta24" type="radiolist" domain="" maxlength="250" required="true" change="false" readonly="false" disabled="false" child_size="12" right="false" java-type="">
                    <label/>
                    <list>
                        <option>
                            <text>Option 1</text>
                            <value>1</value>
                        </option>
                        <option>
                            <text>Option 2</text>
                            <value>2</value>
                        </option>
                        <option>
                            <text>Option 3</text>
                            <value>3</value>
                        </option>
                        <option>
                            <text>Option 4</text>
                            <value>4</value>
                        </option>
                    </list>
                    <validations>
                        <validation>
                            <annotation>@NotNull</annotation>
                        </validation>
                    </validations>
                </resposta24>
                <pergunta_25_sep name="p_pergunta_25_sep" type="separator" maxlength="250" placeholder="" desclabel="false" right="false">
                    <label>Pergunta 25</label>
                </pergunta_25_sep>
                <pergunta25 name="p_pergunta25" type="plaintext" clear="false" disable_output_escaping="false" html_class="" maxlength="250" right="false">
                    <label>Pergunta25</label>
                    <value>Consectetur stract sit stract sit sit consectetur omnis totam anim elit anim natus sed unde totam ut laudantium lorem ipsum stract lorem mollit totam ut</value>
                </pergunta25>
                <resposta25 name="p_resposta25" type="radiolist" domain="" maxlength="250" required="true" change="false" readonly="false" disabled="false" child_size="12" right="false" java-type="">
                    <label/>
                    <list>
                        <option>
                            <text>Option 1</text>
                            <value>1</value>
                        </option>
                        <option>
                            <text>Option 2</text>
                            <value>2</value>
                        </option>
                        <option>
                            <text>Option 3</text>
                            <value>3</value>
                        </option>
                        <option>
                            <text>Option 4</text>
                            <value>4</value>
                        </option>
                    </list>
                    <validations>
                        <validation>
                            <annotation>@NotNull</annotation>
                        </validation>
                    </validations>
                </resposta25>
                <conceitos_de_base_de_dados_e_dao name="p_conceitos_de_base_de_dados_e_dao" type="separator" maxlength="250" placeholder="" desclabel="false" right="false">
                    <label>CONCEITOS DE BASE DE DADOS E DAO</label>
                </conceitos_de_base_de_dados_e_dao>
                <pergunta_26_sep name="p_pergunta_26_sep" type="separator" maxlength="250" placeholder="" desclabel="false" right="false">
                    <label>Pergunta 26</label>
                </pergunta_26_sep>
                <pergunta26 name="p_pergunta26" type="plaintext" clear="false" disable_output_escaping="false" html_class="" maxlength="250" right="false">
                    <label>Pergunta26</label>
                    <value>Dolor consectetur elit doloremque dolor accusantium anim stract laudantium lorem iste adipiscing perspiciatis stract voluptatem anim rem unde doloremque laudantium iste elit rem officia omnis</value>
                </pergunta26>
                <resposta26 name="p_resposta26" type="radiolist" domain="" maxlength="250" required="true" change="false" readonly="false" disabled="false" child_size="12" right="false" java-type="">
                    <label/>
                    <list>
                        <option>
                            <text>Option 1</text>
                            <value>1</value>
                        </option>
                        <option>
                            <text>Option 2</text>
                            <value>2</value>
                        </option>
                        <option>
                            <text>Option 3</text>
                            <value>3</value>
                        </option>
                        <option>
                            <text>Option 4</text>
                            <value>4</value>
                        </option>
                    </list>
                    <validations>
                        <validation>
                            <annotation>@NotNull</annotation>
                        </validation>
                    </validations>
                </resposta26>
                <pergunta_27_sep name="p_pergunta_27_sep" type="separator" maxlength="250" placeholder="" desclabel="false" right="false">
                    <label>Pergunta 27</label>
                </pergunta_27_sep>
                <pergunta27 name="p_pergunta27" type="plaintext" clear="false" disable_output_escaping="false" html_class="" maxlength="250" right="false">
                    <label>Pergunta27</label>
                    <value>Elit adipiscing sit voluptatem deserunt sit natus aliqua natus aperiam lorem ut doloremque magna ut adipiscing rem amet accusantium deserunt mollit labore laudantium officia sit</value>
                </pergunta27>
                <resposta27 name="p_resposta27" type="radiolist" domain="" maxlength="250" required="true" change="false" readonly="false" disabled="false" child_size="12" right="false" java-type="">
                    <label/>
                    <list>
                        <option>
                            <text>Option 1</text>
                            <value>1</value>
                        </option>
                        <option>
                            <text>Option 2</text>
                            <value>2</value>
                        </option>
                        <option>
                            <text>Option 3</text>
                            <value>3</value>
                        </option>
                        <option>
                            <text>Option 4</text>
                            <value>4</value>
                        </option>
                    </list>
                    <validations>
                        <validation>
                            <annotation>@NotNull</annotation>
                        </validation>
                    </validations>
                </resposta27>
                <pergunta_28_sep name="p_pergunta_28_sep" type="separator" maxlength="250" placeholder="" desclabel="false" right="false">
                    <label>Pergunta 28</label>
                </pergunta_28_sep>
                <pergunta28 name="p_pergunta28" type="plaintext" clear="false" disable_output_escaping="false" html_class="" maxlength="250" right="false">
                    <label>Pergunta28</label>
                    <value>Sit ipsum mollit sed officia lorem sit deserunt ipsum consectetur accusantium doloremque adipiscing consectetur laudantium aperiam adipiscing stract totam natus sit stract totam consectetur voluptatem</value>
                </pergunta28>
                <resposta28 name="p_resposta28" type="radiolist" domain="" maxlength="250" required="true" change="false" readonly="false" disabled="false" child_size="12" right="false" java-type="">
                    <label/>
                    <list>
                        <option>
                            <text>Option 1</text>
                            <value>1</value>
                        </option>
                        <option>
                            <text>Option 2</text>
                            <value>2</value>
                        </option>
                        <option>
                            <text>Option 3</text>
                            <value>3</value>
                        </option>
                        <option>
                            <text>Option 4</text>
                            <value>4</value>
                        </option>
                    </list>
                    <validations>
                        <validation>
                            <annotation>@NotNull</annotation>
                        </validation>
                    </validations>
                </resposta28>
                <pergunta_29_sep name="p_pergunta_29_sep" type="separator" maxlength="250" placeholder="" desclabel="false" right="false">
                    <label>Pergunta 29</label>
                </pergunta_29_sep>
                <pergunta29 name="p_pergunta29" type="plaintext" clear="false" disable_output_escaping="false" html_class="" maxlength="250" right="false">
                    <label>Pergunta29</label>
                    <value>Doloremque magna amet sit iste aliqua natus sit sit magna rem aliqua sit labore sit dolor totam aliqua sit accusantium elit aliqua mollit ut sit</value>
                </pergunta29>
                <resposta29 name="p_resposta29" type="radiolist" domain="" maxlength="250" required="true" change="false" readonly="false" disabled="false" child_size="12" right="false" java-type="">
                    <label/>
                    <list>
                        <option>
                            <text>Option 1</text>
                            <value>1</value>
                        </option>
                        <option>
                            <text>Option 2</text>
                            <value>2</value>
                        </option>
                        <option>
                            <text>Option 3</text>
                            <value>3</value>
                        </option>
                        <option>
                            <text>Option 4</text>
                            <value>4</value>
                        </option>
                    </list>
                </resposta29>
                <pergunta_30_sep name="p_pergunta_30_sep" type="separator" maxlength="250" placeholder="" desclabel="false" right="false">
                    <label>Pergunta 30</label>
                </pergunta_30_sep>
                <pergunta30 name="p_pergunta30" type="plaintext" clear="false" disable_output_escaping="false" html_class="" maxlength="250" right="false">
                    <label>Pergunta30</label>
                    <value>Natus mollit aperiam stract ut mollit amet unde lorem sit elit unde elit officia aperiam anim magna elit laudantium sit magna sit elit stract doloremque</value>
                </pergunta30>
                <resposta30 name="p_resposta30" type="radiolist" domain="" maxlength="250" required="true" change="false" readonly="false" disabled="false" child_size="12" right="false" java-type="">
                    <label/>
                    <list>
                        <option>
                            <text>Option 1</text>
                            <value>1</value>
                        </option>
                        <option>
                            <text>Option 2</text>
                            <value>2</value>
                        </option>
                        <option>
                            <text>Option 3</text>
                            <value>3</value>
                        </option>
                        <option>
                            <text>Option 4</text>
                            <value>4</value>
                        </option>
                    </list>
                    <validations>
                        <validation>
                            <annotation>@NotNull</annotation>
                        </validation>
                    </validations>
                </resposta30>
                <conceitos_de_java name="p_conceitos_de_java" type="separator" maxlength="250" placeholder="" desclabel="false" right="false">
                    <label>CONCEITOS DE JAVA</label>
                </conceitos_de_java>
                <pergunta_31_sep name="p_pergunta_31_sep" type="separator" maxlength="250" placeholder="" desclabel="false" right="false">
                    <label>Pergunta 31</label>
                </pergunta_31_sep>
                <pergunta31 name="p_pergunta31" type="plaintext" clear="false" disable_output_escaping="false" html_class="" maxlength="250" right="false">
                    <label>Pergunta31</label>
                    <value>Deserunt sit doloremque dolor natus anim consectetur sit magna lorem anim doloremque deserunt officia aperiam mollit elit sit ipsum deserunt aliqua voluptatem laudantium sit stract</value>
                </pergunta31>
                <resposta31 name="p_resposta31" type="radiolist" domain="" maxlength="250" required="true" change="false" readonly="false" disabled="false" child_size="12" right="false" java-type="">
                    <label/>
                    <list>
                        <option>
                            <text>Option 1</text>
                            <value>1</value>
                        </option>
                        <option>
                            <text>Option 2</text>
                            <value>2</value>
                        </option>
                        <option>
                            <text>Option 3</text>
                            <value>3</value>
                        </option>
                        <option>
                            <text>Option 4</text>
                            <value>4</value>
                        </option>
                    </list>
                    <validations>
                        <validation>
                            <annotation>@NotNull</annotation>
                        </validation>
                    </validations>
                </resposta31>
                <pergunta_32_sep name="p_pergunta_32_sep" type="separator" maxlength="250" placeholder="" desclabel="false" right="false">
                    <label>Pergunta 32</label>
                </pergunta_32_sep>
                <pergunta32 name="p_pergunta32" type="plaintext" clear="false" disable_output_escaping="false" html_class="" maxlength="250" right="false">
                    <label>Pergunta32</label>
                    <value>Rem sed deserunt natus unde officia magna rem natus labore sed ut natus omnis deserunt mollit totam stract laudantium perspiciatis rem accusantium unde aliqua ut</value>
                </pergunta32>
                <resposta32 name="p_resposta32" type="radiolist" domain="" maxlength="250" required="true" change="false" readonly="false" disabled="false" child_size="12" right="false" java-type="">
                    <label/>
                    <list>
                        <option>
                            <text>Option 1</text>
                            <value>1</value>
                        </option>
                        <option>
                            <text>Option 2</text>
                            <value>2</value>
                        </option>
                        <option>
                            <text>Option 3</text>
                            <value>3</value>
                        </option>
                        <option>
                            <text>Option 4</text>
                            <value>4</value>
                        </option>
                    </list>
                    <validations>
                        <validation>
                            <annotation>@NotNull</annotation>
                        </validation>
                    </validations>
                </resposta32>
                <pergunta_33_sep name="p_pergunta_33_sep" type="separator" maxlength="250" placeholder="" desclabel="false" right="false">
                    <label>Pergunta 33</label>
                </pergunta_33_sep>
                <pergunta33 name="p_pergunta33" type="plaintext" clear="false" disable_output_escaping="false" html_class="" maxlength="250" right="false">
                    <label>Pergunta33</label>
                    <value>Lorem aliqua totam adipiscing sit labore adipiscing accusantium adipiscing deserunt omnis totam elit sit totam accusantium aliqua iste stract labore accusantium ut magna stract doloremque</value>
                </pergunta33>
                <resposta33 name="p_resposta33" type="radiolist" domain="" maxlength="250" required="true" change="false" readonly="false" disabled="false" child_size="12" right="false" java-type="">
                    <label/>
                    <list>
                        <option>
                            <text>Option 1</text>
                            <value>1</value>
                        </option>
                        <option>
                            <text>Option 2</text>
                            <value>2</value>
                        </option>
                        <option>
                            <text>Option 3</text>
                            <value>3</value>
                        </option>
                        <option>
                            <text>Option 4</text>
                            <value>4</value>
                        </option>
                    </list>
                </resposta33>
                <perungta_34_sep name="p_perungta_34_sep" type="separator" maxlength="250" placeholder="" desclabel="false" right="false">
                    <label>Perungta 34</label>
                </perungta_34_sep>
                <pergunta34 name="p_pergunta34" type="plaintext" clear="false" disable_output_escaping="false" html_class="" maxlength="250" right="false">
                    <label>Pergunta34</label>
                    <value>Ut dolor laudantium doloremque dolor amet laudantium unde ipsum aliqua amet omnis unde sed aliqua officia elit iste rem labore ut mollit doloremque amet adipiscing</value>
                </pergunta34>
                <resposta34 name="p_resposta34" type="radiolist" domain="" maxlength="250" required="true" change="false" readonly="false" disabled="false" child_size="12" right="false" java-type="">
                    <label/>
                    <list>
                        <option>
                            <text>Option 1</text>
                            <value>1</value>
                        </option>
                        <option>
                            <text>Option 2</text>
                            <value>2</value>
                        </option>
                        <option>
                            <text>Option 3</text>
                            <value>3</value>
                        </option>
                        <option>
                            <text>Option 4</text>
                            <value>4</value>
                        </option>
                    </list>
                </resposta34>
                <perungta_35_sep name="p_perungta_35_sep" type="separator" maxlength="250" placeholder="" desclabel="false" right="false">
                    <label>Perungta 35</label>
                </perungta_35_sep>
                <pergunta35 name="p_pergunta35" type="plaintext" clear="false" disable_output_escaping="false" html_class="" maxlength="250" right="false">
                    <label>Pergunta35</label>
                    <value>Perspiciatis totam ut perspiciatis mollit amet rem totam ipsum aperiam adipiscing sit ut consectetur mollit sit elit unde consectetur dolor mollit elit unde amet ipsum</value>
                </pergunta35>
                <resposta35 name="p_resposta35" type="radiolist" domain="" maxlength="250" required="true" change="false" readonly="false" disabled="false" child_size="12" right="false" java-type="">
                    <label/>
                    <list>
                        <option>
                            <text>Option 1</text>
                            <value>1</value>
                        </option>
                        <option>
                            <text>Option 2</text>
                            <value>2</value>
                        </option>
                        <option>
                            <text>Option 3</text>
                            <value>3</value>
                        </option>
                        <option>
                            <text>Option 4</text>
                            <value>4</value>
                        </option>
                    </list>
                </resposta35>
                <conceitos_de_gestao_de_acessos name="p_conceitos_de_gestao_de_acessos" type="separator" maxlength="250" placeholder="" desclabel="false" right="false">
                    <label>CONCEITOS DE GESTÃO DE ACESSOS</label>
                </conceitos_de_gestao_de_acessos>
                <pergunta_36_sep name="p_pergunta_36_sep" type="separator" maxlength="250" placeholder="" desclabel="false" right="false">
                    <label>Pergunta 36</label>
                </pergunta_36_sep>
                <pergunta_36 name="p_pergunta_36" type="plaintext" clear="false" disable_output_escaping="false" html_class="" maxlength="250" right="false">
                    <label>Pergunta 36</label>
                    <value>Aliqua lorem natus magna consectetur natus unde aperiam accusantium laudantium natus voluptatem aliqua ut laudantium dolor totam adipiscing accusantium dolor ut natus sed mollit consectetur</value>
                </pergunta_36>
                <resposta36 name="p_resposta36" type="radiolist" domain="" maxlength="250" required="true" change="false" readonly="false" disabled="false" child_size="12" right="false" java-type="">
                    <label/>
                    <list>
                        <option>
                            <text>Option 1</text>
                            <value>1</value>
                        </option>
                        <option>
                            <text>Option 2</text>
                            <value>2</value>
                        </option>
                        <option>
                            <text>Option 3</text>
                            <value>3</value>
                        </option>
                        <option>
                            <text>Option 4</text>
                            <value>4</value>
                        </option>
                    </list>
                    <validations>
                        <validation>
                            <annotation>@NotNull</annotation>
                        </validation>
                    </validations>
                </resposta36>
                <pergunta_37_sep name="p_pergunta_37_sep" type="separator" maxlength="250" placeholder="" desclabel="false" right="false">
                    <label>Pergunta 37</label>
                </pergunta_37_sep>
                <pergunta_37 name="p_pergunta_37" type="plaintext" clear="false" disable_output_escaping="false" html_class="" maxlength="250" right="false">
                    <label>Pergunta 37</label>
                    <value>Aliqua iste sed aliqua laudantium perspiciatis elit dolor adipiscing consectetur elit aliqua consectetur deserunt dolor perspiciatis ut aliqua elit aliqua totam natus perspiciatis adipiscing aliqua</value>
                </pergunta_37>
                <resposta37 name="p_resposta37" type="radiolist" domain="" maxlength="250" required="true" change="false" readonly="false" disabled="false" child_size="12" right="false" java-type="">
                    <label/>
                    <list>
                        <option>
                            <text>Option 1</text>
                            <value>1</value>
                        </option>
                        <option>
                            <text>Option 2</text>
                            <value>2</value>
                        </option>
                        <option>
                            <text>Option 3</text>
                            <value>3</value>
                        </option>
                        <option>
                            <text>Option 4</text>
                            <value>4</value>
                        </option>
                    </list>
                    <validations>
                        <validation>
                            <annotation>@NotNull</annotation>
                        </validation>
                    </validations>
                </resposta37>
                <pergunta_38_sep name="p_pergunta_38_sep" type="separator" maxlength="250" placeholder="" desclabel="false" right="false">
                    <label>Pergunta 38</label>
                </pergunta_38_sep>
                <pergunta_38 name="p_pergunta_38" type="plaintext" clear="false" disable_output_escaping="false" html_class="" maxlength="250" right="false">
                    <label>Pergunta 38</label>
                    <value>Dolor adipiscing totam aliqua sit sit adipiscing consectetur sed magna anim consectetur sit labore sit elit lorem ut consectetur deserunt anim perspiciatis adipiscing totam ut</value>
                </pergunta_38>
                <resposta38 name="p_resposta38" type="radiolist" domain="" maxlength="250" required="true" change="false" readonly="false" disabled="false" child_size="12" right="false" java-type="">
                    <label/>
                    <list>
                        <option>
                            <text>Option 1</text>
                            <value>1</value>
                        </option>
                        <option>
                            <text>Option 2</text>
                            <value>2</value>
                        </option>
                        <option>
                            <text>Option 3</text>
                            <value>3</value>
                        </option>
                        <option>
                            <text>Option 4</text>
                            <value>4</value>
                        </option>
                    </list>
                    <validations>
                        <validation>
                            <annotation>@NotNull</annotation>
                        </validation>
                    </validations>
                </resposta38>
                <pergunta_39_sep name="p_pergunta_39_sep" type="separator" maxlength="250" placeholder="" desclabel="false" right="false">
                    <label>Pergunta 39</label>
                </pergunta_39_sep>
                <pergunta_39 name="p_pergunta_39" type="plaintext" clear="false" disable_output_escaping="false" html_class="" maxlength="250" right="false">
                    <label>Pergunta 39</label>
                    <value>Totam accusantium laudantium aperiam officia consectetur unde amet sed sit deserunt accusantium ut deserunt stract doloremque ipsum magna voluptatem adipiscing ipsum totam aperiam mollit sit</value>
                </pergunta_39>
                <resposta39 name="p_resposta39" type="radiolist" domain="" maxlength="250" required="true" change="false" readonly="false" disabled="false" child_size="12" right="false" java-type="">
                    <label/>
                    <list>
                        <option>
                            <text>Option 1</text>
                            <value>1</value>
                        </option>
                        <option>
                            <text>Option 2</text>
                            <value>2</value>
                        </option>
                        <option>
                            <text>Option 3</text>
                            <value>3</value>
                        </option>
                        <option>
                            <text>Option 4</text>
                            <value>4</value>
                        </option>
                    </list>
                    <validations>
                        <validation>
                            <annotation>@NotNull</annotation>
                        </validation>
                    </validations>
                </resposta39>
                <pergunta_40_sep name="p_pergunta_40_sep" type="separator" maxlength="250" placeholder="" desclabel="false" right="false">
                    <label>Pergunta 40</label>
                </pergunta_40_sep>
                <pergunta_40 name="p_pergunta_40" type="plaintext" clear="false" disable_output_escaping="false" html_class="" maxlength="250" right="false">
                    <label>Pergunta 40</label>
                    <value>Iste mollit doloremque perspiciatis unde sed sit dolor natus labore magna doloremque lorem aperiam labore adipiscing dolor aliqua anim mollit rem officia ipsum aperiam totam</value>
                </pergunta_40>
                <resposta40 name="p_resposta40" type="radiolist" domain="" maxlength="250" required="true" change="false" readonly="false" disabled="false" child_size="12" right="false" java-type="">
                    <label/>
                    <list>
                        <option>
                            <text>Option 1</text>
                            <value>1</value>
                        </option>
                        <option>
                            <text>Option 2</text>
                            <value>2</value>
                        </option>
                        <option>
                            <text>Option 3</text>
                            <value>3</value>
                        </option>
                        <option>
                            <text>Option 4</text>
                            <value>4</value>
                        </option>
                    </list>
                    <validations>
                        <validation>
                            <annotation>@NotNull</annotation>
                        </validation>
                    </validations>
                </resposta40>
                <hidden name="p_id_avaliado" type="hidden" maxlength="250" java-type="" tag="id_avaliado"/>
                <hidden name="p_nivel" type="hidden" maxlength="250" java-type="" tag="nivel"/>
            </fields>
        </form_1>
    </content>
    <blockly>
        <imports></imports>
        <xml>
            <block type="controller" id="controller" x="388" y="13"></block>
        </xml>
    </blockly>
</rows>
